pysysgit-0.1.0.dist-info/DESCRIPTION.rst
pysysgit-0.1.0.dist-info/METADATA
pysysgit-0.1.0.dist-info/metadata.json
pysysgit-0.1.0.dist-info/RECORD
pysysgit-0.1.0.dist-info/top_level.txt
pysysgit-0.1.0.dist-info/WHEEL
sysgit/__init__.py
sysgit/utils.py
