Metadata-Version: 2.0
Name: pysysgit
Version: 0.1.0
Summary: Utility to call git from python
Home-page: https://github.com/onlynone/pysysgit
Author: Steven Willis
Author-email: onlynone@gmail.com
License: BSD
Keywords: sysgit
Platform: UNKNOWN
Classifier: Development Status :: 2 - Pre-Alpha
Classifier: Intended Audience :: Developers
Classifier: License :: OSI Approved :: BSD License
Classifier: Natural Language :: English
Classifier: Programming Language :: Python :: 2
Classifier: Programming Language :: Python :: 2.6
Classifier: Programming Language :: Python :: 2.7
Classifier: Programming Language :: Python :: 3
Classifier: Programming Language :: Python :: 3.3
Classifier: Programming Language :: Python :: 3.4
